{
  "_guid_": "MidEvent_v1Ext_Citizen__Base",

  "productName": "CCD Data Store",
  "operationName": "validation of a set of fields as Citizen (v1_ext citizen)",

  "method": "POST",
  "uri": "/citizens/{uid}/jurisdictions/{jid}/case-types/{ctid}/validate",

  "request": {
    "headers": {
      "_extends_": "Common_Request_Headers"
    },
    "pathVariables": {
      "uid": "[[DEFAULT_AUTO_VALUE]]",
      "jid": "OVERRIDE",
      "ctid": "OVERRIDE"
    },
    "queryParams": {
      "pageId": "OVERRIDE"
    },
    "body": {
      "data": {},
      "event": {
        "id": "OVERRIDE",
        "summary": "",
        "description": ""
      },
      "security_classification": "PUBLIC",
      "event_token" : "OVERRIDE",
      "ignore_warning": true
    }
  }
}
