{
  "_guid_": "F-143_Add_Supplementary_Data",
  "title": "Update Supplementary Data Base",
  "productName": "CCD Data Store",
  "operationName": "Update Supplementary Data",
  "method": "POST",
  "uri": "/cases/{caseId}/supplementary-data",
  "specs": ["to add supplementary data for the case"],
  "users": {
    "invokingUser": {
      "_extends_": "BeftaCaseworkerCaa"
    }
  },
  "request": {
    "_extends_": "Common_Request",
    "pathVariables": {
      "caseId": "${[scenarioContext][parentContext][childContexts][F-143_CreateCasePreRequisiteCaseworker][testData][actualResponse][body][id]}"
    },
    "body": {
      "supplementary_data_updates": {
        "$set": {
          "new_case.orgID1": true
        }
      }
    }
  },
  "expectedResponse": {
    "_extends_": "Common_200_Response",
    "body": {
      "supplementary_data": {
        "new_case.orgID1": true
      }
    }
  }
}
