{
  "title": "must return an error response for a malformed Case ID",
  "_guid_": "S-598",
  "_extends_": "F-103_Test_Data_Base",
  "specs": [
    "an active profile in CCD",
    "contains an malformed case ID"
  ],
  "request": {
    "pathVariables": {
      "cid": "157375164884ab@!"
    }
  },
  "expectedResponse": {
    "_extends_": "Common_400_Response",
    "headers": {
      "Content-Encoding" : "gzip"
    },
    "body": {
      "exception": "uk.gov.hmcts.ccd.endpoint.exceptions.BadRequestException",
      "message": "Case ID is not valid",
      "details": null,
      "callbackErrors": null,
      "callbackWarnings": null
    }
  }
}
