{
  "_guid_": "F-13010.3_CreateCase",
  "_extends_" : "F-13010_CreateCaseBase",

  "request": {
    "pathVariables": {
      "ctid": "FT_CaseAccessCategories_1"
    },
    "body": {
      "event_token": "${[scenarioContext][parentContext][childContexts][F-13010.3_CreateCase_Token_Creation][testData][actualResponse][body][token]}",
      "data": {
        "CaseAccessCategory": "FamilyLaw/Standard"
      }
    }
  },

  "expectedResponse": {
    "body" : {
      "case_type" : "FT_CaseAccessCategories_1",
      "data": {
        "CaseAccessCategory": "FamilyLaw/Standard"
      }
    }
  }
}
